spreadg/__init__.py
spreadg/allfun.py
ansh997-0.1.0.dist-info/METADATA
ansh997-0.1.0.dist-info/WHEEL
ansh997-0.1.0.dist-info/top_level.txt
ansh997-0.1.0.dist-info/RECORD
