Metadata-Version: 2.1
Name: ansh997
Version: 0.1.0
Summary: Plot data from Google sheets
Home-page: https://github.com/ansh997/SpreadG
Author: Himanshu Pal
Author-email: palhimanshu997@gmail.com
License: UNKNOWN
Platform: UNKNOWN
Classifier: Programming Language :: Python :: 3
Classifier: License :: OSI Approved :: MIT License
Classifier: Operating System :: OS Independent
Requires-Python: >=3.6
Requires-Dist: pandas
Requires-Dist: matplotlib
Requires-Dist: oauth2client
Requires-Dist: gspread
